[
  {
    "precio": 500,
    "id": 1,
    "title": "Albondigas de pollo con vegetales",
    "img": "../imagenes/albondigas-pollo-veg-ok.jpg"
  },
  {
    "precio": 600,
    "id": 2,
    "title": "Risotto con champignones",
    "img": "../imagenes/arroz-goulash-ok.jpg"
  },
  {
    "precio": 400,
    "id": 3,
    "title": "Curry de garbanzos con arroz",
    "img": "https://raw.githubusercontent.com/MicaelaTovo/js-coder/main/Imagenes/curry-garbanzos-arroz.jpg"
  },
  {
    "precio": 700,
    "id": 4,
    "title": "Lasagna de carne",
    "img": "https://raw.githubusercontent.com/MicaelaTovo/js-coder/main/Imagenes/lasagna-ok.jpg"
  },
  {
    "precio": 720,
    "id": 5,
    "title": "Pescado con espinaca a la crema",
    "img": "https://raw.githubusercontent.com/MicaelaTovo/js-coder/main/Imagenes/pescado-espinaca-ok.jpg"
  },
  {
    "precio": 480,
    "id": 6,
    "title": "Pizza integral con cebolla, individual",
    "img": "https://raw.githubusercontent.com/MicaelaTovo/js-coder/main/Imagenes/pizza-integral-cebolla-ok.jpg"
  },
  {
      "precio": 600,
      "id": 7,
      "title": "Pollo con verduras",
      "img": "https://raw.githubusercontent.com/MicaelaTovo/js-coder/main/Imagenes/pollo-gril-vegetales-ok.jpg"
    },
    {
      "precio": 450,
      "id": 8,
      "title": "Tarta integral de vegetales",
      "img": "https://raw.githubusercontent.com/MicaelaTovo/js-coder/main/Imagenes/tarta-integral-vegetales-ok.jpg"
    },
    {
      "precio": 480,
      "id": 9,
      "title": "Fideos con bolognesa",
      "img": "https://raw.githubusercontent.com/MicaelaTovo/js-coder/main/Imagenes/fideos-bolognesa-ok.jpg"
    },
    {
      "precio": 500,
      "id": 10,
      "title": "Falafels con arroz y vegetales",
      "img": "https://raw.githubusercontent.com/MicaelaTovo/js-coder/main/Imagenes/falafel-arroz-vegetales-ok.jpg"
    },
    {
      "precio": 800,
      "id": 11,
      "title": "Carne con verduras",
      "img": "https://raw.githubusercontent.com/MicaelaTovo/js-coder/main/Imagenes/carne-veg-ok.jpg"
    },
    {
      "precio": 650,
      "id": 12,
      "title": "wok de pollo teriyaki",
      "img": "https://raw.githubusercontent.com/MicaelaTovo/js-coder/main/Imagenes/pollo-teriyaki-wok-ok.jpg"
    }
  
]